Workbook

Sheet Configuracion
A1: Variable | B1: Valor
A2: TC_Actual | B2: 3.35
A3: Ganancia_USD | B3: 90
A4: Transporte_USD | B4: 80
A5: Impuesto_Importacion | B5: 0.07
A6: Comision_Tarjeta | B6: 0.05

Sheet Catalogo
A1: id | B1: name | C1: brand | D1: price | E1: condition | F1: grade | G1: featured | H1: Costo_Fabrica_64GB_USD | I1: Costo_Fabrica_128GB_USD | J1: Costo_Fabrica_256GB_USD | K1: Costo_Fabrica_512GB_USD | L1: Costo_Fabrica_1TB_USD | M1: Costo_Fabrica_2TB_USD | N1: Precio_Venta_64GB_PEN | O1: Precio_Venta_128GB_PEN | P1: Precio_Venta_256GB_PEN | Q1: Precio_Venta_512GB_PEN | R1: Precio_Venta_1TB_PEN | S1: Precio_Venta_2TB_PEN
A2: 107 | B2: iPhone 17 | C2: Apple | D2: 4999 | E2: new | F2: Nuevo Sellado | G2: TRUE | J2: 821.47 | K2: 1016.03 | N2: =IF(H2="", "", ROUND((H2+Configuracion!$B$3+Configuracion!$B$4)*(1+Configuracion!$B$5+Configuracion!$B$6)*Configuracion!$B$2, -1)) | O2: =IF(I2="", "", ROUND((I2+Configuracion!$B$3+Configuracion!$B$4)*(1+Configuracion!$B$5+Configuracion!$B$6)*Configuracion!$B$2, -1)) | P2: =IF(J2="", "", ROUND((J2+Configuracion!$B$3+Configuracion!$B$4)*(1+Configuracion!$B$5+Configuracion!$B$6)*Configuracion!$B$2, -1)) | Q2: =IF(K2="", "", ROUND((K2+Configuracion!$B$3+Configuracion!$B$4)*(1+Configuracion!$B$5+Configuracion!$B$6)*Configuracion!$B$2, -1)) | R2: =IF(L2="", "", ROUND((L2+Configuracion!$B$3+Configuracion!$B$4)*(1+Configuracion!$B$5+Configuracion!$B$6)*Configuracion!$B$2, -1)) | S2: =IF(M2="", "", ROUND((M2+Configuracion!$B$3+Configuracion!$B$4)*(1+Configuracion!$B$5+Configuracion!$B$6)*Configuracion!$B$2, -1))
A3: 108 | B3: iPhone Air | C3: Apple | D3: 5499 | E3: new | F3: Nuevo Sellado | G3: TRUE | J3: 981.39 | K3: 1181.28 | L3: 1381.17 | N3: =IF(H3="", "", ROUND((H3+Configuracion!$B$3+Configuracion!$B$4)*(1+Configuracion!$B$5+Configuracion!$B$6)*Configuracion!$B$2, -1)) | O3: =IF(I3="", "", ROUND((I3+Configuracion!$B$3+Configuracion!$B$4)*(1+Configuracion!$B$5+Configuracion!$B$6)*Configuracion!$B$2, -1)) | P3: =IF(J3="", "", ROUND((J3+Configuracion!$B$3+Configuracion!$B$4)*(1+Configuracion!$B$5+Configuracion!$B$6)*Configuracion!$B$2, -1)) | Q3: =IF(K3="", "", ROUND((K3+Configuracion!$B$3+Configuracion!$B$4)*(1+Configuracion!$B$5+Configuracion!$B$6)*Configuracion!$B$2, -1)) | R3: =IF(L3="", "", ROUND((L3+Configuracion!$B$3+Configuracion!$B$4)*(1+Configuracion!$B$5+Configuracion!$B$6)*Configuracion!$B$2, -1)) | S3: =IF(M3="", "", ROUND((M3+Configuracion!$B$3+Configuracion!$B$4)*(1+Configuracion!$B$5+Configuracion!$B$6)*Configuracion!$B$2, -1))
A4: 109 | B4: iPhone 17 Pro | C4: Apple | D4: 5999 | E4: new | F4: Nuevo Sellado | G4: TRUE | J4: 1074.67 | K4: 1282.56 | L4: 1482.45 | N4: =IF(H4="", "", ROUND((H4+Configuracion!$B$3+Configuracion!$B$4)*(1+Configuracion!$B$5+Configuracion!$B$6)*Configuracion!$B$2, -1)) | O4: =IF(I4="", "", ROUND((I4+Configuracion!$B$3+Configuracion!$B$4)*(1+Configuracion!$B$5+Configuracion!$B$6)*Configuracion!$B$2, -1)) | P4: =IF(J4="", "", ROUND((J4+Configuracion!$B$3+Configuracion!$B$4)*(1+Configuracion!$B$5+Configuracion!$B$6)*Configuracion!$B$2, -1)) | Q4: =IF(K4="", "", ROUND((K4+Configuracion!$B$3+Configuracion!$B$4)*(1+Configuracion!$B$5+Configuracion!$B$6)*Configuracion!$B$2, -1)) | R4: =IF(L4="", "", ROUND((L4+Configuracion!$B$3+Configuracion!$B$4)*(1+Configuracion!$B$5+Configuracion!$B$6)*Configuracion!$B$2, -1)) | S4: =IF(M4="", "", ROUND((M4+Configuracion!$B$3+Configuracion!$B$4)*(1+Configuracion!$B$5+Configuracion!$B$6)*Configuracion!$B$2, -1))
A5: 110 | B5: iPhone 17 Pro Max | C5: Apple | D5: 6599 | E5: new | F5: Nuevo Sellado | G5: TRUE | J5: 1181.28 | K5: 1381.17 | L5: 1581.07 | M5: 1980.85 | N5: =IF(H5="", "", ROUND((H5+Configuracion!$B$3+Configuracion!$B$4)*(1+Configuracion!$B$5+Configuracion!$B$6)*Configuracion!$B$2, -1)) | O5: =IF(I5="", "", ROUND((I5+Configuracion!$B$3+Configuracion!$B$4)*(1+Configuracion!$B$5+Configuracion!$B$6)*Configuracion!$B$2, -1)) | P5: =IF(J5="", "", ROUND((J5+Configuracion!$B$3+Configuracion!$B$4)*(1+Configuracion!$B$5+Configuracion!$B$6)*Configuracion!$B$2, -1)) | Q5: =IF(K5="", "", ROUND((K5+Configuracion!$B$3+Configuracion!$B$4)*(1+Configuracion!$B$5+Configuracion!$B$6)*Configuracion!$B$2, -1)) | R5: =IF(L5="", "", ROUND((L5+Configuracion!$B$3+Configuracion!$B$4)*(1+Configuracion!$B$5+Configuracion!$B$6)*Configuracion!$B$2, -1)) | S5: =IF(M5="", "", ROUND((M5+Configuracion!$B$3+Configuracion!$B$4)*(1+Configuracion!$B$5+Configuracion!$B$6)*Configuracion!$B$2, -1))
A6: 111 | B6: iPhone 16 | C6: Apple | D6: 3999 | E6: new | F6: Nuevo Sellado | G6: FALSE | I6: 709.53 | J6: 762.84 | N6: =IF(H6="", "", ROUND((H6+Configuracion!$B$3+Configuracion!$B$4)*(1+Configuracion!$B$5+Configuracion!$B$6)*Configuracion!$B$2, -1)) | O6: =IF(I6="", "", ROUND((I6+Configuracion!$B$3+Configuracion!$B$4)*(1+Configuracion!$B$5+Configuracion!$B$6)*Configuracion!$B$2, -1)) | P6: =IF(J6="", "", ROUND((J6+Configuracion!$B$3+Configuracion!$B$4)*(1+Configuracion!$B$5+Configuracion!$B$6)*Configuracion!$B$2, -1)) | Q6: =IF(K6="", "", ROUND((K6+Configuracion!$B$3+Configuracion!$B$4)*(1+Configuracion!$B$5+Configuracion!$B$6)*Configuracion!$B$2, -1)) | R6: =IF(L6="", "", ROUND((L6+Configuracion!$B$3+Configuracion!$B$4)*(1+Configuracion!$B$5+Configuracion!$B$6)*Configuracion!$B$2, -1)) | S6: =IF(M6="", "", ROUND((M6+Configuracion!$B$3+Configuracion!$B$4)*(1+Configuracion!$B$5+Configuracion!$B$6)*Configuracion!$B$2, -1))
A7: 112 | B7: iPhone 16 Pro | C7: Apple | D7: 4699 | E7: used | F7: Muy bueno | G7: TRUE | J7: 656.23 | L7: 1508.84 | N7: =IF(H7="", "", ROUND((H7+Configuracion!$B$3+Configuracion!$B$4)*(1+Configuracion!$B$5+Configuracion!$B$6)*Configuracion!$B$2, -1)) | O7: =IF(I7="", "", ROUND((I7+Configuracion!$B$3+Configuracion!$B$4)*(1+Configuracion!$B$5+Configuracion!$B$6)*Configuracion!$B$2, -1)) | P7: =IF(J7="", "", ROUND((J7+Configuracion!$B$3+Configuracion!$B$4)*(1+Configuracion!$B$5+Configuracion!$B$6)*Configuracion!$B$2, -1)) | Q7: =IF(K7="", "", ROUND((K7+Configuracion!$B$3+Configuracion!$B$4)*(1+Configuracion!$B$5+Configuracion!$B$6)*Configuracion!$B$2, -1)) | R7: =IF(L7="", "", ROUND((L7+Configuracion!$B$3+Configuracion!$B$4)*(1+Configuracion!$B$5+Configuracion!$B$6)*Configuracion!$B$2, -1)) | S7: =IF(M7="", "", ROUND((M7+Configuracion!$B$3+Configuracion!$B$4)*(1+Configuracion!$B$5+Configuracion!$B$6)*Configuracion!$B$2, -1))
A8: 113 | B8: iPhone 16 Pro Max | C8: Apple | D8: 5299 | E8: used | F8: Excelente | G8: TRUE | J8: 733.52 | K8: 834.8 | L8: 1535.49 | N8: =IF(H8="", "", ROUND((H8+Configuracion!$B$3+Configuracion!$B$4)*(1+Configuracion!$B$5+Configuracion!$B$6)*Configuracion!$B$2, -1)) | O8: =IF(I8="", "", ROUND((I8+Configuracion!$B$3+Configuracion!$B$4)*(1+Configuracion!$B$5+Configuracion!$B$6)*Configuracion!$B$2, -1)) | P8: =IF(J8="", "", ROUND((J8+Configuracion!$B$3+Configuracion!$B$4)*(1+Configuracion!$B$5+Configuracion!$B$6)*Configuracion!$B$2, -1)) | Q8: =IF(K8="", "", ROUND((K8+Configuracion!$B$3+Configuracion!$B$4)*(1+Configuracion!$B$5+Configuracion!$B$6)*Configuracion!$B$2, -1)) | R8: =IF(L8="", "", ROUND((L8+Configuracion!$B$3+Configuracion!$B$4)*(1+Configuracion!$B$5+Configuracion!$B$6)*Configuracion!$B$2, -1)) | S8: =IF(M8="", "", ROUND((M8+Configuracion!$B$3+Configuracion!$B$4)*(1+Configuracion!$B$5+Configuracion!$B$6)*Configuracion!$B$2, -1))
A9: 106 | B9: iPhone 15 Pro Max | C9: Apple | D9: 5799 | E9: used | F9: Muy bueno | G9: TRUE | I9: 509.64 | J9: 549.62 | K9: 602.92 | N9: =IF(H9="", "", ROUND((H9+Configuracion!$B$3+Configuracion!$B$4)*(1+Configuracion!$B$5+Configuracion!$B$6)*Configuracion!$B$2, -1)) | O9: =IF(I9="", "", ROUND((I9+Configuracion!$B$3+Configuracion!$B$4)*(1+Configuracion!$B$5+Configuracion!$B$6)*Configuracion!$B$2, -1)) | P9: =IF(J9="", "", ROUND((J9+Configuracion!$B$3+Configuracion!$B$4)*(1+Configuracion!$B$5+Configuracion!$B$6)*Configuracion!$B$2, -1)) | Q9: =IF(K9="", "", ROUND((K9+Configuracion!$B$3+Configuracion!$B$4)*(1+Configuracion!$B$5+Configuracion!$B$6)*Configuracion!$B$2, -1)) | R9: =IF(L9="", "", ROUND((L9+Configuracion!$B$3+Configuracion!$B$4)*(1+Configuracion!$B$5+Configuracion!$B$6)*Configuracion!$B$2, -1)) | S9: =IF(M9="", "", ROUND((M9+Configuracion!$B$3+Configuracion!$B$4)*(1+Configuracion!$B$5+Configuracion!$B$6)*Configuracion!$B$2, -1))
A10: 114 | B10: iPhone 15 Pro | C10: Apple | D10: 3899 | E10: used | F10: Excelente | G10: FALSE | I10: 437.68 | J10: 469.66 | N10: =IF(H10="", "", ROUND((H10+Configuracion!$B$3+Configuracion!$B$4)*(1+Configuracion!$B$5+Configuracion!$B$6)*Configuracion!$B$2, -1)) | O10: =IF(I10="", "", ROUND((I10+Configuracion!$B$3+Configuracion!$B$4)*(1+Configuracion!$B$5+Configuracion!$B$6)*Configuracion!$B$2, -1)) | P10: =IF(J10="", "", ROUND((J10+Configuracion!$B$3+Configuracion!$B$4)*(1+Configuracion!$B$5+Configuracion!$B$6)*Configuracion!$B$2, -1)) | Q10: =IF(K10="", "", ROUND((K10+Configuracion!$B$3+Configuracion!$B$4)*(1+Configuracion!$B$5+Configuracion!$B$6)*Configuracion!$B$2, -1)) | R10: =IF(L10="", "", ROUND((L10+Configuracion!$B$3+Configuracion!$B$4)*(1+Configuracion!$B$5+Configuracion!$B$6)*Configuracion!$B$2, -1)) | S10: =IF(M10="", "", ROUND((M10+Configuracion!$B$3+Configuracion!$B$4)*(1+Configuracion!$B$5+Configuracion!$B$6)*Configuracion!$B$2, -1))
A11: 105 | B11: iPhone 15 | C11: Apple | D11: 3599 | E11: used | F11: Bueno | G11: FALSE | I11: 323.07 | J11: 363.05 | N11: =IF(H11="", "", ROUND((H11+Configuracion!$B$3+Configuracion!$B$4)*(1+Configuracion!$B$5+Configuracion!$B$6)*Configuracion!$B$2, -1)) | O11: =IF(I11="", "", ROUND((I11+Configuracion!$B$3+Configuracion!$B$4)*(1+Configuracion!$B$5+Configuracion!$B$6)*Configuracion!$B$2, -1)) | P11: =IF(J11="", "", ROUND((J11+Configuracion!$B$3+Configuracion!$B$4)*(1+Configuracion!$B$5+Configuracion!$B$6)*Configuracion!$B$2, -1)) | Q11: =IF(K11="", "", ROUND((K11+Configuracion!$B$3+Configuracion!$B$4)*(1+Configuracion!$B$5+Configuracion!$B$6)*Configuracion!$B$2, -1)) | R11: =IF(L11="", "", ROUND((L11+Configuracion!$B$3+Configuracion!$B$4)*(1+Configuracion!$B$5+Configuracion!$B$6)*Configuracion!$B$2, -1)) | S11: =IF(M11="", "", ROUND((M11+Configuracion!$B$3+Configuracion!$B$4)*(1+Configuracion!$B$5+Configuracion!$B$6)*Configuracion!$B$2, -1))
A12: 104 | B12: iPhone 14 Pro Max | C12: Apple | D12: 3899 | E12: used | F12: Excelente | G12: FALSE | I12: 429.68 | J12: 469.66 | N12: =IF(H12="", "", ROUND((H12+Configuracion!$B$3+Configuracion!$B$4)*(1+Configuracion!$B$5+Configuracion!$B$6)*Configuracion!$B$2, -1)) | O12: =IF(I12="", "", ROUND((I12+Configuracion!$B$3+Configuracion!$B$4)*(1+Configuracion!$B$5+Configuracion!$B$6)*Configuracion!$B$2, -1)) | P12: =IF(J12="", "", ROUND((J12+Configuracion!$B$3+Configuracion!$B$4)*(1+Configuracion!$B$5+Configuracion!$B$6)*Configuracion!$B$2, -1)) | Q12: =IF(K12="", "", ROUND((K12+Configuracion!$B$3+Configuracion!$B$4)*(1+Configuracion!$B$5+Configuracion!$B$6)*Configuracion!$B$2, -1)) | R12: =IF(L12="", "", ROUND((L12+Configuracion!$B$3+Configuracion!$B$4)*(1+Configuracion!$B$5+Configuracion!$B$6)*Configuracion!$B$2, -1)) | S12: =IF(M12="", "", ROUND((M12+Configuracion!$B$3+Configuracion!$B$4)*(1+Configuracion!$B$5+Configuracion!$B$6)*Configuracion!$B$2, -1))
A13: 116 | B13: iPhone 14 Pro | C13: Apple | D13: 3099 | E13: used | F13: Bueno | G13: FALSE | I13: 363.05 | J13: 403.03 | N13: =IF(H13="", "", ROUND((H13+Configuracion!$B$3+Configuracion!$B$4)*(1+Configuracion!$B$5+Configuracion!$B$6)*Configuracion!$B$2, -1)) | O13: =IF(I13="", "", ROUND((I13+Configuracion!$B$3+Configuracion!$B$4)*(1+Configuracion!$B$5+Configuracion!$B$6)*Configuracion!$B$2, -1)) | P13: =IF(J13="", "", ROUND((J13+Configuracion!$B$3+Configuracion!$B$4)*(1+Configuracion!$B$5+Configuracion!$B$6)*Configuracion!$B$2, -1)) | Q13: =IF(K13="", "", ROUND((K13+Configuracion!$B$3+Configuracion!$B$4)*(1+Configuracion!$B$5+Configuracion!$B$6)*Configuracion!$B$2, -1)) | R13: =IF(L13="", "", ROUND((L13+Configuracion!$B$3+Configuracion!$B$4)*(1+Configuracion!$B$5+Configuracion!$B$6)*Configuracion!$B$2, -1)) | S13: =IF(M13="", "", ROUND((M13+Configuracion!$B$3+Configuracion!$B$4)*(1+Configuracion!$B$5+Configuracion!$B$6)*Configuracion!$B$2, -1))
A14: 115 | B14: iPhone 14 | C14: Apple | D14: 2599 | E14: used | F14: Bueno | G14: FALSE | I14: 229.79 | J14: 256.44 | N14: =IF(H14="", "", ROUND((H14+Configuracion!$B$3+Configuracion!$B$4)*(1+Configuracion!$B$5+Configuracion!$B$6)*Configuracion!$B$2, -1)) | O14: =IF(I14="", "", ROUND((I14+Configuracion!$B$3+Configuracion!$B$4)*(1+Configuracion!$B$5+Configuracion!$B$6)*Configuracion!$B$2, -1)) | P14: =IF(J14="", "", ROUND((J14+Configuracion!$B$3+Configuracion!$B$4)*(1+Configuracion!$B$5+Configuracion!$B$6)*Configuracion!$B$2, -1)) | Q14: =IF(K14="", "", ROUND((K14+Configuracion!$B$3+Configuracion!$B$4)*(1+Configuracion!$B$5+Configuracion!$B$6)*Configuracion!$B$2, -1)) | R14: =IF(L14="", "", ROUND((L14+Configuracion!$B$3+Configuracion!$B$4)*(1+Configuracion!$B$5+Configuracion!$B$6)*Configuracion!$B$2, -1)) | S14: =IF(M14="", "", ROUND((M14+Configuracion!$B$3+Configuracion!$B$4)*(1+Configuracion!$B$5+Configuracion!$B$6)*Configuracion!$B$2, -1))
A15: 122 | B15: iPhone 13 Pro Max | C15: Apple | D15: 2699 | E15: used | F15: Bueno | G15: FALSE | I15: 363.05 | J15: 389.7 | N15: =IF(H15="", "", ROUND((H15+Configuracion!$B$3+Configuracion!$B$4)*(1+Configuracion!$B$5+Configuracion!$B$6)*Configuracion!$B$2, -1)) | O15: =IF(I15="", "", ROUND((I15+Configuracion!$B$3+Configuracion!$B$4)*(1+Configuracion!$B$5+Configuracion!$B$6)*Configuracion!$B$2, -1)) | P15: =IF(J15="", "", ROUND((J15+Configuracion!$B$3+Configuracion!$B$4)*(1+Configuracion!$B$5+Configuracion!$B$6)*Configuracion!$B$2, -1)) | Q15: =IF(K15="", "", ROUND((K15+Configuracion!$B$3+Configuracion!$B$4)*(1+Configuracion!$B$5+Configuracion!$B$6)*Configuracion!$B$2, -1)) | R15: =IF(L15="", "", ROUND((L15+Configuracion!$B$3+Configuracion!$B$4)*(1+Configuracion!$B$5+Configuracion!$B$6)*Configuracion!$B$2, -1)) | S15: =IF(M15="", "", ROUND((M15+Configuracion!$B$3+Configuracion!$B$4)*(1+Configuracion!$B$5+Configuracion!$B$6)*Configuracion!$B$2, -1))
A16: 121 | B16: iPhone 13 Pro | C16: Apple | D16: 2299 | E16: used | F16: Bueno | G16: FALSE | I16: 283.09 | J16: 323.07 | N16: =IF(H16="", "", ROUND((H16+Configuracion!$B$3+Configuracion!$B$4)*(1+Configuracion!$B$5+Configuracion!$B$6)*Configuracion!$B$2, -1)) | O16: =IF(I16="", "", ROUND((I16+Configuracion!$B$3+Configuracion!$B$4)*(1+Configuracion!$B$5+Configuracion!$B$6)*Configuracion!$B$2, -1)) | P16: =IF(J16="", "", ROUND((J16+Configuracion!$B$3+Configuracion!$B$4)*(1+Configuracion!$B$5+Configuracion!$B$6)*Configuracion!$B$2, -1)) | Q16: =IF(K16="", "", ROUND((K16+Configuracion!$B$3+Configuracion!$B$4)*(1+Configuracion!$B$5+Configuracion!$B$6)*Configuracion!$B$2, -1)) | R16: =IF(L16="", "", ROUND((L16+Configuracion!$B$3+Configuracion!$B$4)*(1+Configuracion!$B$5+Configuracion!$B$6)*Configuracion!$B$2, -1)) | S16: =IF(M16="", "", ROUND((M16+Configuracion!$B$3+Configuracion!$B$4)*(1+Configuracion!$B$5+Configuracion!$B$6)*Configuracion!$B$2, -1))
A17: 120 | B17: iPhone 13 | C17: Apple | D17: 1899 | E17: used | F17: Excelente | G17: FALSE | I17: 203.13 | J17: 229.79 | N17: =IF(H17="", "", ROUND((H17+Configuracion!$B$3+Configuracion!$B$4)*(1+Configuracion!$B$5+Configuracion!$B$6)*Configuracion!$B$2, -1)) | O17: =IF(I17="", "", ROUND((I17+Configuracion!$B$3+Configuracion!$B$4)*(1+Configuracion!$B$5+Configuracion!$B$6)*Configuracion!$B$2, -1)) | P17: =IF(J17="", "", ROUND((J17+Configuracion!$B$3+Configuracion!$B$4)*(1+Configuracion!$B$5+Configuracion!$B$6)*Configuracion!$B$2, -1)) | Q17: =IF(K17="", "", ROUND((K17+Configuracion!$B$3+Configuracion!$B$4)*(1+Configuracion!$B$5+Configuracion!$B$6)*Configuracion!$B$2, -1)) | R17: =IF(L17="", "", ROUND((L17+Configuracion!$B$3+Configuracion!$B$4)*(1+Configuracion!$B$5+Configuracion!$B$6)*Configuracion!$B$2, -1)) | S17: =IF(M17="", "", ROUND((M17+Configuracion!$B$3+Configuracion!$B$4)*(1+Configuracion!$B$5+Configuracion!$B$6)*Configuracion!$B$2, -1))
A18: 123 | B18: iPhone 12 Pro Max | C18: Apple | D18: 2399 | E18: used | F18: Bueno | G18: FALSE | I18: 269.77 | J18: 309.74 | N18: =IF(H18="", "", ROUND((H18+Configuracion!$B$3+Configuracion!$B$4)*(1+Configuracion!$B$5+Configuracion!$B$6)*Configuracion!$B$2, -1)) | O18: =IF(I18="", "", ROUND((I18+Configuracion!$B$3+Configuracion!$B$4)*(1+Configuracion!$B$5+Configuracion!$B$6)*Configuracion!$B$2, -1)) | P18: =IF(J18="", "", ROUND((J18+Configuracion!$B$3+Configuracion!$B$4)*(1+Configuracion!$B$5+Configuracion!$B$6)*Configuracion!$B$2, -1)) | Q18: =IF(K18="", "", ROUND((K18+Configuracion!$B$3+Configuracion!$B$4)*(1+Configuracion!$B$5+Configuracion!$B$6)*Configuracion!$B$2, -1)) | R18: =IF(L18="", "", ROUND((L18+Configuracion!$B$3+Configuracion!$B$4)*(1+Configuracion!$B$5+Configuracion!$B$6)*Configuracion!$B$2, -1)) | S18: =IF(M18="", "", ROUND((M18+Configuracion!$B$3+Configuracion!$B$4)*(1+Configuracion!$B$5+Configuracion!$B$6)*Configuracion!$B$2, -1))
A19: 119 | B19: iPhone 12 Pro | C19: Apple | D19: 2099 | E19: used | F19: Excelente | G19: FALSE | I19: 216.46 | J19: 243.11 | N19: =IF(H19="", "", ROUND((H19+Configuracion!$B$3+Configuracion!$B$4)*(1+Configuracion!$B$5+Configuracion!$B$6)*Configuracion!$B$2, -1)) | O19: =IF(I19="", "", ROUND((I19+Configuracion!$B$3+Configuracion!$B$4)*(1+Configuracion!$B$5+Configuracion!$B$6)*Configuracion!$B$2, -1)) | P19: =IF(J19="", "", ROUND((J19+Configuracion!$B$3+Configuracion!$B$4)*(1+Configuracion!$B$5+Configuracion!$B$6)*Configuracion!$B$2, -1)) | Q19: =IF(K19="", "", ROUND((K19+Configuracion!$B$3+Configuracion!$B$4)*(1+Configuracion!$B$5+Configuracion!$B$6)*Configuracion!$B$2, -1)) | R19: =IF(L19="", "", ROUND((L19+Configuracion!$B$3+Configuracion!$B$4)*(1+Configuracion!$B$5+Configuracion!$B$6)*Configuracion!$B$2, -1)) | S19: =IF(M19="", "", ROUND((M19+Configuracion!$B$3+Configuracion!$B$4)*(1+Configuracion!$B$5+Configuracion!$B$6)*Configuracion!$B$2, -1))
A20: 102 | B20: iPhone 12 | C20: Apple | D20: 1599 | E20: used | F20: Bueno | G20: FALSE | H20: 43.22 | I20: 149.83 | N20: =IF(H20="", "", ROUND((H20+Configuracion!$B$3+Configuracion!$B$4)*(1+Configuracion!$B$5+Configuracion!$B$6)*Configuracion!$B$2, -1)) | O20: =IF(I20="", "", ROUND((I20+Configuracion!$B$3+Configuracion!$B$4)*(1+Configuracion!$B$5+Configuracion!$B$6)*Configuracion!$B$2, -1)) | P20: =IF(J20="", "", ROUND((J20+Configuracion!$B$3+Configuracion!$B$4)*(1+Configuracion!$B$5+Configuracion!$B$6)*Configuracion!$B$2, -1)) | Q20: =IF(K20="", "", ROUND((K20+Configuracion!$B$3+Configuracion!$B$4)*(1+Configuracion!$B$5+Configuracion!$B$6)*Configuracion!$B$2, -1)) | R20: =IF(L20="", "", ROUND((L20+Configuracion!$B$3+Configuracion!$B$4)*(1+Configuracion!$B$5+Configuracion!$B$6)*Configuracion!$B$2, -1)) | S20: =IF(M20="", "", ROUND((M20+Configuracion!$B$3+Configuracion!$B$4)*(1+Configuracion!$B$5+Configuracion!$B$6)*Configuracion!$B$2, -1))
A21: 101 | B21: iPhone 11 | C21: Apple | D21: 1299 | E21: used | F21: Bueno | G21: FALSE | H21: 29.89 | I21: 56.55 | N21: =IF(H21="", "", ROUND((H21+Configuracion!$B$3+Configuracion!$B$4)*(1+Configuracion!$B$5+Configuracion!$B$6)*Configuracion!$B$2, -1)) | O21: =IF(I21="", "", ROUND((I21+Configuracion!$B$3+Configuracion!$B$4)*(1+Configuracion!$B$5+Configuracion!$B$6)*Configuracion!$B$2, -1)) | P21: =IF(J21="", "", ROUND((J21+Configuracion!$B$3+Configuracion!$B$4)*(1+Configuracion!$B$5+Configuracion!$B$6)*Configuracion!$B$2, -1)) | Q21: =IF(K21="", "", ROUND((K21+Configuracion!$B$3+Configuracion!$B$4)*(1+Configuracion!$B$5+Configuracion!$B$6)*Configuracion!$B$2, -1)) | R21: =IF(L21="", "", ROUND((L21+Configuracion!$B$3+Configuracion!$B$4)*(1+Configuracion!$B$5+Configuracion!$B$6)*Configuracion!$B$2, -1)) | S21: =IF(M21="", "", ROUND((M21+Configuracion!$B$3+Configuracion!$B$4)*(1+Configuracion!$B$5+Configuracion!$B$6)*Configuracion!$B$2, -1))
A22: 215 | B22: Google Pixel 10 Pro XL | C22: Google | D22: 4999 | E22: new | F22: Nuevo Sellado | G22: TRUE | J22: 1175.95 | K22: 1295.88 | L22: 1527.76 | N22: =IF(H22="", "", ROUND((H22+Configuracion!$B$3+Configuracion!$B$4)*(1+Configuracion!$B$5+Configuracion!$B$6)*Configuracion!$B$2, -1)) | O22: =IF(I22="", "", ROUND((I22+Configuracion!$B$3+Configuracion!$B$4)*(1+Configuracion!$B$5+Configuracion!$B$6)*Configuracion!$B$2, -1)) | P22: =IF(J22="", "", ROUND((J22+Configuracion!$B$3+Configuracion!$B$4)*(1+Configuracion!$B$5+Configuracion!$B$6)*Configuracion!$B$2, -1)) | Q22: =IF(K22="", "", ROUND((K22+Configuracion!$B$3+Configuracion!$B$4)*(1+Configuracion!$B$5+Configuracion!$B$6)*Configuracion!$B$2, -1)) | R22: =IF(L22="", "", ROUND((L22+Configuracion!$B$3+Configuracion!$B$4)*(1+Configuracion!$B$5+Configuracion!$B$6)*Configuracion!$B$2, -1)) | S22: =IF(M22="", "", ROUND((M22+Configuracion!$B$3+Configuracion!$B$4)*(1+Configuracion!$B$5+Configuracion!$B$6)*Configuracion!$B$2, -1))
A23: 214 | B23: Google Pixel 10 Pro | C23: Google | D23: 4499 | E23: new | F23: Nuevo Sellado | G23: TRUE | I23: 994.71 | J23: 1095.99 | K23: 1215.93 | L23: 1447.8 | N23: =IF(H23="", "", ROUND((H23+Configuracion!$B$3+Configuracion!$B$4)*(1+Configuracion!$B$5+Configuracion!$B$6)*Configuracion!$B$2, -1)) | O23: =IF(I23="", "", ROUND((I23+Configuracion!$B$3+Configuracion!$B$4)*(1+Configuracion!$B$5+Configuracion!$B$6)*Configuracion!$B$2, -1)) | P23: =IF(J23="", "", ROUND((J23+Configuracion!$B$3+Configuracion!$B$4)*(1+Configuracion!$B$5+Configuracion!$B$6)*Configuracion!$B$2, -1)) | Q23: =IF(K23="", "", ROUND((K23+Configuracion!$B$3+Configuracion!$B$4)*(1+Configuracion!$B$5+Configuracion!$B$6)*Configuracion!$B$2, -1)) | R23: =IF(L23="", "", ROUND((L23+Configuracion!$B$3+Configuracion!$B$4)*(1+Configuracion!$B$5+Configuracion!$B$6)*Configuracion!$B$2, -1)) | S23: =IF(M23="", "", ROUND((M23+Configuracion!$B$3+Configuracion!$B$4)*(1+Configuracion!$B$5+Configuracion!$B$6)*Configuracion!$B$2, -1))
A24: 213 | B24: Google Pixel 10 | C24: Google | D24: 3499 | E24: new | F24: Nuevo Sellado | G24: TRUE | I24: 793.49 | J24: 896.1 | N24: =IF(H24="", "", ROUND((H24+Configuracion!$B$3+Configuracion!$B$4)*(1+Configuracion!$B$5+Configuracion!$B$6)*Configuracion!$B$2, -1)) | O24: =IF(I24="", "", ROUND((I24+Configuracion!$B$3+Configuracion!$B$4)*(1+Configuracion!$B$5+Configuracion!$B$6)*Configuracion!$B$2, -1)) | P24: =IF(J24="", "", ROUND((J24+Configuracion!$B$3+Configuracion!$B$4)*(1+Configuracion!$B$5+Configuracion!$B$6)*Configuracion!$B$2, -1)) | Q24: =IF(K24="", "", ROUND((K24+Configuracion!$B$3+Configuracion!$B$4)*(1+Configuracion!$B$5+Configuracion!$B$6)*Configuracion!$B$2, -1)) | R24: =IF(L24="", "", ROUND((L24+Configuracion!$B$3+Configuracion!$B$4)*(1+Configuracion!$B$5+Configuracion!$B$6)*Configuracion!$B$2, -1)) | S24: =IF(M24="", "", ROUND((M24+Configuracion!$B$3+Configuracion!$B$4)*(1+Configuracion!$B$5+Configuracion!$B$6)*Configuracion!$B$2, -1))
A25: 216 | B25: Google Pixel 10a | C25: Google | D25: 2299 | E25: new | F25: Nuevo Sellado | G25: FALSE | I25: 442.74 | J25: 576 | N25: =IF(H25="", "", ROUND((H25+Configuracion!$B$3+Configuracion!$B$4)*(1+Configuracion!$B$5+Configuracion!$B$6)*Configuracion!$B$2, -1)) | O25: =IF(I25="", "", ROUND((I25+Configuracion!$B$3+Configuracion!$B$4)*(1+Configuracion!$B$5+Configuracion!$B$6)*Configuracion!$B$2, -1)) | P25: =IF(J25="", "", ROUND((J25+Configuracion!$B$3+Configuracion!$B$4)*(1+Configuracion!$B$5+Configuracion!$B$6)*Configuracion!$B$2, -1)) | Q25: =IF(K25="", "", ROUND((K25+Configuracion!$B$3+Configuracion!$B$4)*(1+Configuracion!$B$5+Configuracion!$B$6)*Configuracion!$B$2, -1)) | R25: =IF(L25="", "", ROUND((L25+Configuracion!$B$3+Configuracion!$B$4)*(1+Configuracion!$B$5+Configuracion!$B$6)*Configuracion!$B$2, -1)) | S25: =IF(M25="", "", ROUND((M25+Configuracion!$B$3+Configuracion!$B$4)*(1+Configuracion!$B$5+Configuracion!$B$6)*Configuracion!$B$2, -1))
A26: 212 | B26: Google Pixel 9 Pro XL | C26: Google | D26: 3999 | E26: used | F26: Excelente | G26: TRUE | I26: 469.66 | J26: 1029.09 | K26: 1162.36 | L26: 1295.62 | N26: =IF(H26="", "", ROUND((H26+Configuracion!$B$3+Configuracion!$B$4)*(1+Configuracion!$B$5+Configuracion!$B$6)*Configuracion!$B$2, -1)) | O26: =IF(I26="", "", ROUND((I26+Configuracion!$B$3+Configuracion!$B$4)*(1+Configuracion!$B$5+Configuracion!$B$6)*Configuracion!$B$2, -1)) | P26: =IF(J26="", "", ROUND((J26+Configuracion!$B$3+Configuracion!$B$4)*(1+Configuracion!$B$5+Configuracion!$B$6)*Configuracion!$B$2, -1)) | Q26: =IF(K26="", "", ROUND((K26+Configuracion!$B$3+Configuracion!$B$4)*(1+Configuracion!$B$5+Configuracion!$B$6)*Configuracion!$B$2, -1)) | R26: =IF(L26="", "", ROUND((L26+Configuracion!$B$3+Configuracion!$B$4)*(1+Configuracion!$B$5+Configuracion!$B$6)*Configuracion!$B$2, -1)) | S26: =IF(M26="", "", ROUND((M26+Configuracion!$B$3+Configuracion!$B$4)*(1+Configuracion!$B$5+Configuracion!$B$6)*Configuracion!$B$2, -1))
A27: 211 | B27: Google Pixel 9 Pro | C27: Google | D27: 3499 | E27: used | F27: Excelente | G27: TRUE | I27: 416.35 | J27: 895.83 | K27: 1029.09 | L27: 1162.36 | N27: =IF(H27="", "", ROUND((H27+Configuracion!$B$3+Configuracion!$B$4)*(1+Configuracion!$B$5+Configuracion!$B$6)*Configuracion!$B$2, -1)) | O27: =IF(I27="", "", ROUND((I27+Configuracion!$B$3+Configuracion!$B$4)*(1+Configuracion!$B$5+Configuracion!$B$6)*Configuracion!$B$2, -1)) | P27: =IF(J27="", "", ROUND((J27+Configuracion!$B$3+Configuracion!$B$4)*(1+Configuracion!$B$5+Configuracion!$B$6)*Configuracion!$B$2, -1)) | Q27: =IF(K27="", "", ROUND((K27+Configuracion!$B$3+Configuracion!$B$4)*(1+Configuracion!$B$5+Configuracion!$B$6)*Configuracion!$B$2, -1)) | R27: =IF(L27="", "", ROUND((L27+Configuracion!$B$3+Configuracion!$B$4)*(1+Configuracion!$B$5+Configuracion!$B$6)*Configuracion!$B$2, -1)) | S27: =IF(M27="", "", ROUND((M27+Configuracion!$B$3+Configuracion!$B$4)*(1+Configuracion!$B$5+Configuracion!$B$6)*Configuracion!$B$2, -1))
A28: 210 | B28: Google Pixel 9 | C28: Google | D28: 2799 | E28: used | F28: Open Box | G28: TRUE | I28: 376.38 | J28: 709.26 | N28: =IF(H28="", "", ROUND((H28+Configuracion!$B$3+Configuracion!$B$4)*(1+Configuracion!$B$5+Configuracion!$B$6)*Configuracion!$B$2, -1)) | O28: =IF(I28="", "", ROUND((I28+Configuracion!$B$3+Configuracion!$B$4)*(1+Configuracion!$B$5+Configuracion!$B$6)*Configuracion!$B$2, -1)) | P28: =IF(J28="", "", ROUND((J28+Configuracion!$B$3+Configuracion!$B$4)*(1+Configuracion!$B$5+Configuracion!$B$6)*Configuracion!$B$2, -1)) | Q28: =IF(K28="", "", ROUND((K28+Configuracion!$B$3+Configuracion!$B$4)*(1+Configuracion!$B$5+Configuracion!$B$6)*Configuracion!$B$2, -1)) | R28: =IF(L28="", "", ROUND((L28+Configuracion!$B$3+Configuracion!$B$4)*(1+Configuracion!$B$5+Configuracion!$B$6)*Configuracion!$B$2, -1)) | S28: =IF(M28="", "", ROUND((M28+Configuracion!$B$3+Configuracion!$B$4)*(1+Configuracion!$B$5+Configuracion!$B$6)*Configuracion!$B$2, -1))
A29: 217 | B29: Google Pixel 9a | C29: Google | D29: 1999 | E29: used | F29: Open Box | G29: TRUE | I29: 296.42 | J29: 496.04 | N29: =IF(H29="", "", ROUND((H29+Configuracion!$B$3+Configuracion!$B$4)*(1+Configuracion!$B$5+Configuracion!$B$6)*Configuracion!$B$2, -1)) | O29: =IF(I29="", "", ROUND((I29+Configuracion!$B$3+Configuracion!$B$4)*(1+Configuracion!$B$5+Configuracion!$B$6)*Configuracion!$B$2, -1)) | P29: =IF(J29="", "", ROUND((J29+Configuracion!$B$3+Configuracion!$B$4)*(1+Configuracion!$B$5+Configuracion!$B$6)*Configuracion!$B$2, -1)) | Q29: =IF(K29="", "", ROUND((K29+Configuracion!$B$3+Configuracion!$B$4)*(1+Configuracion!$B$5+Configuracion!$B$6)*Configuracion!$B$2, -1)) | R29: =IF(L29="", "", ROUND((L29+Configuracion!$B$3+Configuracion!$B$4)*(1+Configuracion!$B$5+Configuracion!$B$6)*Configuracion!$B$2, -1)) | S29: =IF(M29="", "", ROUND((M29+Configuracion!$B$3+Configuracion!$B$4)*(1+Configuracion!$B$5+Configuracion!$B$6)*Configuracion!$B$2, -1))
A30: 206 | B30: Google Pixel 8 Pro | C30: Google | D30: 3699 | E30: used | F30: Bueno | G30: TRUE | I30: 309.74 | J30: 336.4 | N30: =IF(H30="", "", ROUND((H30+Configuracion!$B$3+Configuracion!$B$4)*(1+Configuracion!$B$5+Configuracion!$B$6)*Configuracion!$B$2, -1)) | O30: =IF(I30="", "", ROUND((I30+Configuracion!$B$3+Configuracion!$B$4)*(1+Configuracion!$B$5+Configuracion!$B$6)*Configuracion!$B$2, -1)) | P30: =IF(J30="", "", ROUND((J30+Configuracion!$B$3+Configuracion!$B$4)*(1+Configuracion!$B$5+Configuracion!$B$6)*Configuracion!$B$2, -1)) | Q30: =IF(K30="", "", ROUND((K30+Configuracion!$B$3+Configuracion!$B$4)*(1+Configuracion!$B$5+Configuracion!$B$6)*Configuracion!$B$2, -1)) | R30: =IF(L30="", "", ROUND((L30+Configuracion!$B$3+Configuracion!$B$4)*(1+Configuracion!$B$5+Configuracion!$B$6)*Configuracion!$B$2, -1)) | S30: =IF(M30="", "", ROUND((M30+Configuracion!$B$3+Configuracion!$B$4)*(1+Configuracion!$B$5+Configuracion!$B$6)*Configuracion!$B$2, -1))
A31: 205 | B31: Google Pixel 8 | C31: Google | D31: 2799 | E31: used | F31: Excelente | G31: FALSE | I31: 216.46 | J31: 296.42 | N31: =IF(H31="", "", ROUND((H31+Configuracion!$B$3+Configuracion!$B$4)*(1+Configuracion!$B$5+Configuracion!$B$6)*Configuracion!$B$2, -1)) | O31: =IF(I31="", "", ROUND((I31+Configuracion!$B$3+Configuracion!$B$4)*(1+Configuracion!$B$5+Configuracion!$B$6)*Configuracion!$B$2, -1)) | P31: =IF(J31="", "", ROUND((J31+Configuracion!$B$3+Configuracion!$B$4)*(1+Configuracion!$B$5+Configuracion!$B$6)*Configuracion!$B$2, -1)) | Q31: =IF(K31="", "", ROUND((K31+Configuracion!$B$3+Configuracion!$B$4)*(1+Configuracion!$B$5+Configuracion!$B$6)*Configuracion!$B$2, -1)) | R31: =IF(L31="", "", ROUND((L31+Configuracion!$B$3+Configuracion!$B$4)*(1+Configuracion!$B$5+Configuracion!$B$6)*Configuracion!$B$2, -1)) | S31: =IF(M31="", "", ROUND((M31+Configuracion!$B$3+Configuracion!$B$4)*(1+Configuracion!$B$5+Configuracion!$B$6)*Configuracion!$B$2, -1))
A32: 209 | B32: Google Pixel 8a | C32: Google | D32: 1499 | E32: used | F32: Bueno | G32: FALSE | I32: 176.48 | N32: =IF(H32="", "", ROUND((H32+Configuracion!$B$3+Configuracion!$B$4)*(1+Configuracion!$B$5+Configuracion!$B$6)*Configuracion!$B$2, -1)) | O32: =IF(I32="", "", ROUND((I32+Configuracion!$B$3+Configuracion!$B$4)*(1+Configuracion!$B$5+Configuracion!$B$6)*Configuracion!$B$2, -1)) | P32: =IF(J32="", "", ROUND((J32+Configuracion!$B$3+Configuracion!$B$4)*(1+Configuracion!$B$5+Configuracion!$B$6)*Configuracion!$B$2, -1)) | Q32: =IF(K32="", "", ROUND((K32+Configuracion!$B$3+Configuracion!$B$4)*(1+Configuracion!$B$5+Configuracion!$B$6)*Configuracion!$B$2, -1)) | R32: =IF(L32="", "", ROUND((L32+Configuracion!$B$3+Configuracion!$B$4)*(1+Configuracion!$B$5+Configuracion!$B$6)*Configuracion!$B$2, -1)) | S32: =IF(M32="", "", ROUND((M32+Configuracion!$B$3+Configuracion!$B$4)*(1+Configuracion!$B$5+Configuracion!$B$6)*Configuracion!$B$2, -1))
A33: 204 | B33: Google Pixel 7 Pro | C33: Google | D33: 2499 | E33: used | F33: Bueno | G33: FALSE | I33: 65.87 | J33: 149.83 | N33: =IF(H33="", "", ROUND((H33+Configuracion!$B$3+Configuracion!$B$4)*(1+Configuracion!$B$5+Configuracion!$B$6)*Configuracion!$B$2, -1)) | O33: =IF(I33="", "", ROUND((I33+Configuracion!$B$3+Configuracion!$B$4)*(1+Configuracion!$B$5+Configuracion!$B$6)*Configuracion!$B$2, -1)) | P33: =IF(J33="", "", ROUND((J33+Configuracion!$B$3+Configuracion!$B$4)*(1+Configuracion!$B$5+Configuracion!$B$6)*Configuracion!$B$2, -1)) | Q33: =IF(K33="", "", ROUND((K33+Configuracion!$B$3+Configuracion!$B$4)*(1+Configuracion!$B$5+Configuracion!$B$6)*Configuracion!$B$2, -1)) | R33: =IF(L33="", "", ROUND((L33+Configuracion!$B$3+Configuracion!$B$4)*(1+Configuracion!$B$5+Configuracion!$B$6)*Configuracion!$B$2, -1)) | S33: =IF(M33="", "", ROUND((M33+Configuracion!$B$3+Configuracion!$B$4)*(1+Configuracion!$B$5+Configuracion!$B$6)*Configuracion!$B$2, -1))
A34: 203 | B34: Google Pixel 7 | C34: Google | D34: 1899 | E34: used | F34: Bueno | G34: FALSE | I34: 45.88 | J34: 72.54 | N34: =IF(H34="", "", ROUND((H34+Configuracion!$B$3+Configuracion!$B$4)*(1+Configuracion!$B$5+Configuracion!$B$6)*Configuracion!$B$2, -1)) | O34: =IF(I34="", "", ROUND((I34+Configuracion!$B$3+Configuracion!$B$4)*(1+Configuracion!$B$5+Configuracion!$B$6)*Configuracion!$B$2, -1)) | P34: =IF(J34="", "", ROUND((J34+Configuracion!$B$3+Configuracion!$B$4)*(1+Configuracion!$B$5+Configuracion!$B$6)*Configuracion!$B$2, -1)) | Q34: =IF(K34="", "", ROUND((K34+Configuracion!$B$3+Configuracion!$B$4)*(1+Configuracion!$B$5+Configuracion!$B$6)*Configuracion!$B$2, -1)) | R34: =IF(L34="", "", ROUND((L34+Configuracion!$B$3+Configuracion!$B$4)*(1+Configuracion!$B$5+Configuracion!$B$6)*Configuracion!$B$2, -1)) | S34: =IF(M34="", "", ROUND((M34+Configuracion!$B$3+Configuracion!$B$4)*(1+Configuracion!$B$5+Configuracion!$B$6)*Configuracion!$B$2, -1))
A35: 208 | B35: Google Pixel 7a | C35: Google | D35: 6000 | E35: used | F35: Bueno | G35: FALSE | N35: =IF(H35="", "", ROUND((H35+Configuracion!$B$3+Configuracion!$B$4)*(1+Configuracion!$B$5+Configuracion!$B$6)*Configuracion!$B$2, -1)) | O35: =IF(I35="", "", ROUND((I35+Configuracion!$B$3+Configuracion!$B$4)*(1+Configuracion!$B$5+Configuracion!$B$6)*Configuracion!$B$2, -1)) | P35: =IF(J35="", "", ROUND((J35+Configuracion!$B$3+Configuracion!$B$4)*(1+Configuracion!$B$5+Configuracion!$B$6)*Configuracion!$B$2, -1)) | Q35: =IF(K35="", "", ROUND((K35+Configuracion!$B$3+Configuracion!$B$4)*(1+Configuracion!$B$5+Configuracion!$B$6)*Configuracion!$B$2, -1)) | R35: =IF(L35="", "", ROUND((L35+Configuracion!$B$3+Configuracion!$B$4)*(1+Configuracion!$B$5+Configuracion!$B$6)*Configuracion!$B$2, -1)) | S35: =IF(M35="", "", ROUND((M35+Configuracion!$B$3+Configuracion!$B$4)*(1+Configuracion!$B$5+Configuracion!$B$6)*Configuracion!$B$2, -1))
A36: 202 | B36: Google Pixel 6 Pro | C36: Google | D36: 1399 | E36: used | F36: Bueno | G36: FALSE | I36: 35.22 | J36: 56.55 | N36: =IF(H36="", "", ROUND((H36+Configuracion!$B$3+Configuracion!$B$4)*(1+Configuracion!$B$5+Configuracion!$B$6)*Configuracion!$B$2, -1)) | O36: =IF(I36="", "", ROUND((I36+Configuracion!$B$3+Configuracion!$B$4)*(1+Configuracion!$B$5+Configuracion!$B$6)*Configuracion!$B$2, -1)) | P36: =IF(J36="", "", ROUND((J36+Configuracion!$B$3+Configuracion!$B$4)*(1+Configuracion!$B$5+Configuracion!$B$6)*Configuracion!$B$2, -1)) | Q36: =IF(K36="", "", ROUND((K36+Configuracion!$B$3+Configuracion!$B$4)*(1+Configuracion!$B$5+Configuracion!$B$6)*Configuracion!$B$2, -1)) | R36: =IF(L36="", "", ROUND((L36+Configuracion!$B$3+Configuracion!$B$4)*(1+Configuracion!$B$5+Configuracion!$B$6)*Configuracion!$B$2, -1)) | S36: =IF(M36="", "", ROUND((M36+Configuracion!$B$3+Configuracion!$B$4)*(1+Configuracion!$B$5+Configuracion!$B$6)*Configuracion!$B$2, -1))
A37: 201 | B37: Google Pixel 6 | C37: Google | D37: 1099 | E37: used | F37: Bueno | G37: FALSE | I37: 21.9 | N37: =IF(H37="", "", ROUND((H37+Configuracion!$B$3+Configuracion!$B$4)*(1+Configuracion!$B$5+Configuracion!$B$6)*Configuracion!$B$2, -1)) | O37: =IF(I37="", "", ROUND((I37+Configuracion!$B$3+Configuracion!$B$4)*(1+Configuracion!$B$5+Configuracion!$B$6)*Configuracion!$B$2, -1)) | P37: =IF(J37="", "", ROUND((J37+Configuracion!$B$3+Configuracion!$B$4)*(1+Configuracion!$B$5+Configuracion!$B$6)*Configuracion!$B$2, -1)) | Q37: =IF(K37="", "", ROUND((K37+Configuracion!$B$3+Configuracion!$B$4)*(1+Configuracion!$B$5+Configuracion!$B$6)*Configuracion!$B$2, -1)) | R37: =IF(L37="", "", ROUND((L37+Configuracion!$B$3+Configuracion!$B$4)*(1+Configuracion!$B$5+Configuracion!$B$6)*Configuracion!$B$2, -1)) | S37: =IF(M37="", "", ROUND((M37+Configuracion!$B$3+Configuracion!$B$4)*(1+Configuracion!$B$5+Configuracion!$B$6)*Configuracion!$B$2, -1))
A38: 207 | B38: Google Pixel 6a | C38: Google | D38: 899 | E38: used | F38: Bueno | G38: TRUE | I38: 8.57 | N38: =IF(H38="", "", ROUND((H38+Configuracion!$B$3+Configuracion!$B$4)*(1+Configuracion!$B$5+Configuracion!$B$6)*Configuracion!$B$2, -1)) | O38: =IF(I38="", "", ROUND((I38+Configuracion!$B$3+Configuracion!$B$4)*(1+Configuracion!$B$5+Configuracion!$B$6)*Configuracion!$B$2, -1)) | P38: =IF(J38="", "", ROUND((J38+Configuracion!$B$3+Configuracion!$B$4)*(1+Configuracion!$B$5+Configuracion!$B$6)*Configuracion!$B$2, -1)) | Q38: =IF(K38="", "", ROUND((K38+Configuracion!$B$3+Configuracion!$B$4)*(1+Configuracion!$B$5+Configuracion!$B$6)*Configuracion!$B$2, -1)) | R38: =IF(L38="", "", ROUND((L38+Configuracion!$B$3+Configuracion!$B$4)*(1+Configuracion!$B$5+Configuracion!$B$6)*Configuracion!$B$2, -1)) | S38: =IF(M38="", "", ROUND((M38+Configuracion!$B$3+Configuracion!$B$4)*(1+Configuracion!$B$5+Configuracion!$B$6)*Configuracion!$B$2, -1))
